AUTHORS
CHANGES.rst
LICENSE
MANIFEST.in
README.rst
setup.cfg
setup.py
tests.py
beproud/__init__.py
beproud/django/__init__.py
beproud/django/ssl/__init__.py
beproud/django/ssl/conf.py
beproud/django/ssl/context_processors.py
beproud/django/ssl/decorators.py
beproud/django/ssl/middleware.py
beproud/django/ssl/models.py
beproud/django/ssl/tests/__init__.py
beproud/django/ssl/tests/base.py
beproud/django/ssl/tests/test_context_processors.py
beproud/django/ssl/tests/test_proxy.py
beproud/django/ssl/tests/test_wsgi.py
beproud/django/ssl/tests/urls.py
bpssl.egg-info/PKG-INFO
bpssl.egg-info/SOURCES.txt
bpssl.egg-info/dependency_links.txt
bpssl.egg-info/namespace_packages.txt
bpssl.egg-info/requires.txt
bpssl.egg-info/top_level.txt
docs/Makefile
docs/en/Makefile
docs/en/source/conf.py
docs/en/source/index.rst
docs/en/source/install.rst
docs/en/source/settings.rst
docs/en/source/usage.rst
docs/en/source/static/beproud.png
docs/ja/Makefile
docs/ja/ja.json
docs/ja/source/conf.py
docs/ja/source/index.rst
docs/ja/source/install.rst
docs/ja/source/settings.rst
docs/ja/source/usage.rst
docs/ja/source/static/beproud.png