Metadata-Version: 1.1
Name: bpssl
Version: 1.0.3
Summary: SSL/HTTPS for Django
Home-page: http://bitbucket.org/beproud/bpssl/
Author: Ian Lewis
Author-email: ian@beproud.jp
License: UNKNOWN
Platform: UNKNOWN
Classifier: Development Status :: 5 - Production/Stable
Classifier: Framework :: Django
Classifier: Environment :: Plugins
Classifier: Environment :: Web Environment
Classifier: Intended Audience :: Developers
Classifier: License :: OSI Approved :: BSD License
Classifier: Operating System :: OS Independent
Classifier: Programming Language :: Python
Classifier: Programming Language :: Python :: 3
Classifier: Topic :: Software Development :: Libraries :: Python Modules
